drive/__init__.py
drive/config.json
drive/dendrogram/__init__.py
drive/dendrogram/dendrogram_subcommand.py
drive/drive.py
drive/network/__init__.py
drive/network/cluster/__init__.py
drive/network/cluster/cluster.py
drive/network/factory/__init__.py
drive/network/factory/factory.py
drive/network/factory/loader.py
drive/network/filters/__init__.py
drive/network/filters/filter.py
drive/network/models/__init__.py
drive/network/models/data_container.py
drive/network/models/generate_indices.py
drive/network/models/networks.py
drive/network/models/types.py
drive/network/network_algorithm.py
drive/phecode_mappings/phecode1.2.txt
drive/phecode_mappings/phecodeX.txt
drive/plugins/__init__.py
drive/plugins/network_writer.py
drive/plugins/pvalues.py
drive/profile.json
drive/utilities/callbacks/__init__.py
drive/utilities/callbacks/callbacks.py
drive/utilities/functions/__init__.py
drive/utilities/functions/split_region_str.py
drive/utilities/parser/__init__.py
drive/utilities/parser/case_file_parser.py
drive/utilities/parser/cmdline_parser.py
drive/utilities/parser/phenotype_descriptions_parser.py
drive/utilities/pull_samples/__init__.py
drive/utilities/pull_samples/pull_sample_ids.py
drive/utilities/testing/__init__.py
drive/utilities/testing/run_integration_test.py
drive_ibd-3.0.3.dist-info/METADATA
drive_ibd-3.0.3.dist-info/WHEEL
drive_ibd-3.0.3.dist-info/entry_points.txt
drive_ibd-3.0.3.dist-info/licenses/LICENSE
tests/__pycache__/__init__.cpython-38.pyc
tests/__pycache__/test_filter.cpython-311-pytest-7.2.2.pyc
tests/__pycache__/test_filter.cpython-311-pytest-8.3.5.pyc
tests/__pycache__/test_integration.cpython-311-pytest-7.2.2.pyc
tests/__pycache__/test_integration.cpython-311-pytest-8.3.5.pyc
tests/__pycache__/test_integration.cpython-311-pytest-8.4.1.pyc
tests/__pycache__/test_integration.cpython-312-pytest-8.4.1.pyc
tests/__pycache__/test_integration.cpython-38-pytest-7.2.2.pyc
tests/__pycache__/test_phecode_descriptions.cpython-311-pytest-7.2.2.pyc
tests/__pycache__/test_phecode_descriptions.cpython-311-pytest-8.3.5.pyc
tests/__pycache__/test_phenotype_file_parser.cpython-311-pytest-7.2.2.pyc
drive_ibd-3.0.3.dist-info/RECORD
