Metadata-Version: 2.1
Name: drive-ibd
Version: 3.0.3
Summary: Python CLI using graph theory to identify networks of individuals who share IBD segments overlapping loci of interest
Keywords: python,genetics,identity by descent,relatedness
Author-Email: James Baker <james.baker@vanderbilt.edu>, Hung-Hsin Chen <hung-hsin.chen.1@vumc.org>, "Jennifer E. Below" <jennifer.e.below@vumc.org>
Maintainer-Email: James Baker <james.baker@vanderbilt.edu>, Hung-Hsin Chen <hung-hsin.chen.1@vumc.org>
License: Apache-2.0
Classifier: Development Status :: 5 - Production/Stable
Classifier: Operating System :: Unix
Classifier: Programming Language :: Python :: 3.10
Classifier: Programming Language :: Python :: 3.11
Classifier: Programming Language :: Python :: 3.12
Classifier: Programming Language :: Python :: 3.13
Classifier: Programming Language :: Python :: 3.14
Project-URL: homepage, https://drive-ibd.readthedocs.io/en/latest/
Project-URL: repository, https://github.com/belowlab/drive
Requires-Python: !=3.11.0,>=3.10
Requires-Dist: pandas>=2.3.0
Requires-Dist: numpy>=2.0.2
Requires-Dist: igraph>=0.11.9
Requires-Dist: scipy>=1.13.1
Requires-Dist: rich-argparse>=1.7.1
Requires-Dist: modified-logger>=1.1.2
Requires-Dist: pytest>=8.4.1
Requires-Dist: matplotlib>=3.9.4
Requires-Dist: pyarrow>=21.0.0
